meraki/__init__.py
meraki/dashboard.py
meraki/exceptions.py
meraki/modules/__init__.py
meraki/modules/admins.py
meraki/modules/base.py
meraki/modules/clients.py
meraki/modules/devices.py
meraki/modules/networks.py
meraki/modules/organizations.py
meraki/modules/ssids.py
meraki_dashboard_api-1.0.0.dist-info/LICENSE
meraki_dashboard_api-1.0.0.dist-info/METADATA
meraki_dashboard_api-1.0.0.dist-info/WHEEL
meraki_dashboard_api-1.0.0.dist-info/top_level.txt
meraki_dashboard_api-1.0.0.dist-info/RECORD
