Metadata-Version: 2.1
Name: meraki-dashboard-api
Version: 1.0.0
Summary: Meraki Dashboard API
Home-page: https://github.com/fgbs/meraki-dashboard-api
Author: Felipe Barros
Author-email: felipe.barros@gmail.com
License: UNKNOWN
Platform: UNKNOWN
Classifier: Intended Audience :: Developers
Classifier: License :: OSI Approved :: MIT License
Classifier: Topic :: Software Development :: Libraries
Classifier: Topic :: System :: Networking
Requires-Dist: requests
Requires-Dist: requests-toolbelt
Requires-Dist: urllib3
